LICENSE
MANIFEST.in
README.md
setup.cfg
setup.py
scpython/__init__.py
scpython/client.py
scpython.egg-info/PKG-INFO
scpython.egg-info/SOURCES.txt
scpython.egg-info/dependency_links.txt
scpython.egg-info/top_level.txt
scpython/exceptions/__init__.py
scpython/exceptions/article.py
scpython/exceptions/auth.py
scpython/model/__init__.py
scpython/model/article.py
scpython/model/scparticle.py
scpython/options/__init__.py
scpython/options/branch.py
scpython/options/language.py
scpython/util/__init__.py
scpython/util/enum.py