Metadata-Version: 2.1
Name: scpython
Version: 0.2.0
Summary: A package to fetch data from the SCP Foundation
Home-page: https://github.com/SartoRiccardo/scpython
Author: TheSartorsss
License: UNKNOWN
Platform: UNKNOWN
Classifier: Programming Language :: Python :: 3
Classifier: License :: OSI Approved :: MIT License
Classifier: Operating System :: OS Independent
Requires-Python: >=3.6
